yapl/__init__.py
yapl/config/__init__.py
yapl/config/config.py
yapl/config/configloader.py
yapl/data/__init__.py
yapl/data/loader/__init__.py
yapl/data/loader/imageloader.py
yapl/engine/__init__.py
yapl/engine/unimodalBinaryClassifer.py
yapl/setup/__init__.py
yapl/setup/backup.py
yapl/setup/googleColab.py
yapl/setup/setupDocker.py
yapl/utils/__init__.py
yapl/utils/accuracy.py
yapl/utils/callbacks.py
yapl/utils/loss.py
yapl/utils/models.py
yapl/utils/sample.py
yapl-0.1.5.dist-info/LICENSE
yapl-0.1.5.dist-info/METADATA
yapl-0.1.5.dist-info/WHEEL
yapl-0.1.5.dist-info/top_level.txt
yapl-0.1.5.dist-info/RECORD
