Metadata-Version: 2.1
Name: yapl
Version: 0.1.5
Summary: yet another python library
Home-page: https://github.com/orionpax00/yapl
Author: Durgesh
Author-email: dkumar@ce.iitr.ac.in
License: APACHE
Platform: UNKNOWN
Classifier: Programming Language :: Python :: 3
Classifier: License :: OSI Approved :: MIT License
Classifier: Operating System :: OS Independent
Requires-Python: >=3.6
